ai_agent_protocol/__init__.py
ai_agent_protocol/didallclient.py
ai_agent_protocol/message_generation.py
ai_agent_protocol/short_term_key_generater.py
ai_agent_protocol/simple_node.py
ai_agent_protocol/simple_node_session.py
ai_agent_protocol/simple_wss_wraper.py
ai_agent_protocol/wss_message_client.py
ai_agent_protocol/wss_message_sdk.py
ai_agent_protocol/utils/__init__.py
ai_agent_protocol/utils/crypto_tool.py
ai_agent_protocol/utils/did_generate.py
ai_agent_protocol/utils/did_verify.py
ai_agent_protocol/utils/log_base.py
didall/__init__.py
didall/didallclient.py
didall/message_generation.py
didall/short_term_key_generater.py
didall/simple_node.py
didall/simple_node_session.py
didall/simple_wss_wraper.py
didall/wss_message_client.py
didall/wss_message_sdk.py
didall/utils/__init__.py
didall/utils/crypto_tool.py
didall/utils/did_generate.py
didall/utils/did_verify.py
didall/utils/log_base.py
tests/__init__.py
tests/run_all_case.py
tests/run_one_case.py
tests/test_did_gen_verify.py
tests/test_http_did_case.py
tests/test_short_term_key.py
tests/test_wss_message_client.py
ai_agent_protocol-0.1.5.dist-info/LICENSE
ai_agent_protocol-0.1.5.dist-info/METADATA
ai_agent_protocol-0.1.5.dist-info/WHEEL
ai_agent_protocol-0.1.5.dist-info/top_level.txt
ai_agent_protocol-0.1.5.dist-info/RECORD
