Metadata-Version: 2.1
Name: ai-agent-protocol
Version: 0.1.5
Summary: An SDK for enabling identity authentication and secure encrypted communication between AI agents.
Home-page: https://github.com/chgaowei/ai-agent-protocol
Author: GaoWei Chang
Author-email: chgaowei@gmail.com
Classifier: Programming Language :: Python :: 3
Classifier: License :: OSI Approved :: MIT License
Classifier: Operating System :: OS Independent
Requires-Python: >=3.7
License-File: LICENSE
Requires-Dist: ecdsa >=0.19.0
Requires-Dist: cryptography >=42.0.8
Requires-Dist: asn1crypto >=1.5.1
Requires-Dist: base58 >=2.1.1
Requires-Dist: aiohttp >=3.9.5
Requires-Dist: requests >=2.32.3
Requires-Dist: websockets >=12.0
